autobound/__init__.py
autobound/elementwise_functions.py
autobound/elementwise_functions_test.py
autobound/enclosure_arithmetic.py
autobound/enclosure_arithmetic_test.py
autobound/graph_editor.py
autobound/graph_editor_test.py
autobound/interval_arithmetic.py
autobound/interval_arithmetic_test.py
autobound/polynomials.py
autobound/polynomials_test.py
autobound/primitive_enclosures.py
autobound/primitive_enclosures_test.py
autobound/test_utils.py
autobound/types.py
autobound/types_test.py
autobound/jax/__init__.py
autobound/jax/jax_bound.py
autobound/jax/jax_bound_test.py
autobound/jax/jaxpr_editor.py
autobound/jax/jaxpr_editor_test.py
autobound-0.1.7.dist-info/licenses/LICENSE
autobound-0.1.7.dist-info/WHEEL
autobound-0.1.7.dist-info/METADATA
autobound-0.1.7.dist-info/RECORD
