Metadata-Version: 2.4
Name: autobound
Version: 0.1.7
Summary: 
Keywords: 
Author-email: AutoBound authors <autobound@google.com>
Requires-Python: >=3.12
Classifier: Programming Language :: Python :: 3
Classifier: Programming Language :: Python :: 3 :: Only
Classifier: License :: OSI Approved :: Apache Software License
Classifier: Intended Audience :: Science/Research
License-File: LICENSE
Requires-Dist: jax>=0.7.2
Requires-Dist: flax>=0.6.7 ; extra == "dev"
Requires-Dist: pytest ; extra == "dev"
Requires-Dist: pytest-xdist ; extra == "dev"
Requires-Dist: pylint>=2.6.0 ; extra == "dev"
Requires-Dist: pyink ; extra == "dev"
Project-URL: homepage, https://github.com/google/autobound
Project-URL: repository, https://github.com/google/autobound
Provides-Extra: dev
